edugrad/__init__.py
edugrad/data.py
edugrad/nn.py
edugrad/ops.py
edugrad/optim.py
edugrad/tensor.py
edugrad-0.0.8.dist-info/LICENSE
edugrad-0.0.8.dist-info/METADATA
edugrad-0.0.8.dist-info/WHEEL
edugrad-0.0.8.dist-info/top_level.txt
edugrad-0.0.8.dist-info/RECORD
