Metadata-Version: 2.1
Name: edugrad
Version: 0.0.8
Summary: Basic computation graph, for pedagogical purposes
Home-page: https://github.com/shanest/edugrad
Author: Shane Steinert-Threlkeld
Author-email: ssshanest@gmail.com
License: UNKNOWN
Platform: UNKNOWN
Classifier: Programming Language :: Python :: 3
Classifier: License :: OSI Approved :: GNU General Public License v3 (GPLv3)
Classifier: Operating System :: OS Independent
Requires-Dist: numpy (>=1.17)
Requires-Dist: networkx (>=2.4)
